har_to_case/__init__.py
har_to_case/main.py
har_to_case/parse_har.py
har_to_case/common/__init__.py
har_to_case/common/tools.py
restore_dependencies/__init__.py
restore_dependencies/main.py
restore_dependencies/src.py
reslib-0.1.2.dist-info/METADATA
reslib-0.1.2.dist-info/WHEEL
reslib-0.1.2.dist-info/entry_points.txt
reslib-0.1.2.dist-info/top_level.txt
reslib-0.1.2.dist-info/zip-safe
reslib-0.1.2.dist-info/RECORD
